ezpykitext/__init__.py
ezpykitext/appkit.py
ezpykitext/config.py
ezpykitext/setup.py
ezpykitext/yaml.py
ezpykitext/enhance/PIL.py
ezpykitext/enhance/__init__.py
ezpykitext/experimental/__init__.py
ezpykitext/experimental/rpc/__init__.py
ezpykitext/experimental/rpc/common.py
ezpykitext/experimental/rpc/nanomsg.py
ezpykitext/os/__init__.py
ezpykitext/os/clipboard/HTMLClipboard.py
ezpykitext/os/clipboard/__init__.py
ezpykitext/os/clipboard/common.py
ezpykitext/os/clipboard/nt.py
ezpykitext/os/clipboard/nt_win32cb.py
ezpykitext/os/clipboard/nt_win32cb_html.py
ezpykitext/os/clipboard/posix.py
ezpykitext/webclient/__init__.py
ezpykitext/webclient/browser.py
ezpykitext/webclient/cookies.py
ezpykitext/webclient/headers.py
ezpykitext/webclient/lxml_html.py
ezpykitext-0.1a0.dev202203161630.dist-info/LICENSE
ezpykitext-0.1a0.dev202203161630.dist-info/METADATA
ezpykitext-0.1a0.dev202203161630.dist-info/WHEEL
ezpykitext-0.1a0.dev202203161630.dist-info/top_level.txt
ezpykitext-0.1a0.dev202203161630.dist-info/RECORD
