Metadata-Version: 2.1
Name: ezpykitext
Version: 0.1a0.dev202203161630
Summary: extend ezpykit
Home-page: https://github.com/mo-han/mo-han-toolbox/tree/master/ezpykitext
Author: mo-han
Author-email: zmhungrown@gmail.com
License: MIT
Platform: UNKNOWN
Classifier: License :: OSI Approved :: MIT License
Classifier: Programming Language :: Python
Classifier: Programming Language :: Python :: 3
Classifier: Programming Language :: Python :: 3.6
Classifier: Programming Language :: Python :: Implementation :: CPython
Classifier: Programming Language :: Python :: Implementation :: PyPy
Requires-Python: >=3.6.0
License-File: LICENSE
